README.rst
exlogging.py
setup.py
test_exlogging.py
exlogging.egg-info/PKG-INFO
exlogging.egg-info/SOURCES.txt
exlogging.egg-info/dependency_links.txt
exlogging.egg-info/not-zip-safe
exlogging.egg-info/pbr.json
exlogging.egg-info/requires.txt
exlogging.egg-info/top_level.txt