Metadata-Version: 1.1
Name: exlogging
Version: 0.1.5
Summary: Supports to setup python standard logging package.
Home-page: https://github.com/narusemotoki/exlogging
Author: Motoki Naruse
Author-email: motoki@naru.se
License: MIT
Keywords: log logging logger
Platform: UNKNOWN
Classifier: Topic :: Utilities
Classifier: Topic :: Software Development
Classifier: Development Status :: 4 - Beta
Classifier: Intended Audience :: Developers
Classifier: License :: OSI Approved :: MIT License
Classifier: Natural Language :: English
Classifier: Operating System :: POSIX
Classifier: Programming Language :: Python
Classifier: Programming Language :: Python :: 3 :: Only
Classifier: Programming Language :: Python :: 3.3
Classifier: Programming Language :: Python :: 3.4
